{"Frazier Moore":{"link":"http://bigstory.ap.org/article/2013-brought-surprises-good-and-bad-viewers","publication":"Associated Press","list":{"Alpha House (Amazon)":"_","Behind the Candelabra (HBO)":"_","Betas (Amazon)":"_","Breaking Bad (AMC)":"_","Downton Abbey (PBS)":"_","The Good Wife (CBS)":"_","House of Cards (Netflix)":"_","Mob City (TNT)":"_","Six by Sondheim (HBO)":"_","Sons of Anarchy (FX)":"_","Sound of Music Live! (NBC)":"_"}},"Aleksander Chan":{"link":"http://bigstory.ap.org/article/2013-brought-surprises-good-and-bad-viewers","publication":"Austin Chronicle","list":{"Breaking Bad (AMC)":1,"The Good Wife (CBS)":2,"Enlightened (HBO)":3,"Black Mirror (DirecTV)":4,"Bunheads (ABC Family)":5,"Orphan Black (BBC America)":6,"30 Rock (NBC)":7,"Orange Is the New Black (Netflix)":8,"Mad Men (AMC)":9,"Scandal (ABC)":10}},"s":{"link":"http://www.avclub.com/article/here-are-links-to-all-of-our-best-of-tv-coverage-f-106615","publication":"AV Club","list":{"Enlightened (HBO)":1,"Breaking Bad (AMC)":2,"Bob's Burgers (Fox)":3},"note":"(other unranked shows omitted because they far exceeded our 10-show cutoff)"},"Ryan McGee":{"link":"http://boobtubedude.com/index.php/2013/12/08/best-of-2013/the-best-tv-of-2013/","publication":"Boob Tube Dude","note":"all others unranked and listed in alphabetical order:","list":{"1. Enlightened (HBO)":"_","1. Orange Is the New Black (Netflix)":"_","The Americans (FX)":"_","Aziz Ansari: Buried Alive (Netflix)":"_","Mike Birbiglia: My Girlfriend's Boyfriend (Netflix)":"_","Bob's Burgers (Fox)":"_","Breaking Bad (AMC)":"_","Justified (FX)":"_","Mad Men (AMC)":"_","Orphan Black (BBC America)":"_","Spartacus (Starz)":"_","Scandal (ABC)":"_","Sleepy Hollow (Fox)":"_"}},"Matthew Gilbert":{"link":"http://www.bostonglobe.com/arts/television/2013/12/28/matthew-gilbert-top-shows/Wy9waKY8ZW95NJhH7MtTeJ/story.html","publication":"Boston Globe","list":{"Breaking Bad (AMC)":1,"Orange Is the New Black (Netflix)":2,"The Good Wife (CBS)":3,"The Americans (FX)":4,"Mad Men (AMC)":5,"Masters of Sex (Showtime)":6,"Vikings (History)":7,"Veep (HBO)":8,"Behind the Candelabra (HBO)":9,"Orphan Black (BBC America)":10}},"Sarah Rodman":{"link":"http://www.bostonglobe.com/arts/television/2013/12/28/sarah-rodman-top-shows/wJQDM6YGKPbqNdjk2OpESO/story.html","publication":"Boston Globe","list":{"Breaking Bad (AMC)":1,"Game of Thrones (HBO)":2,"Masters of Sex (Showtime)":3,"The Good Wife (CBS)":4,"The Americans (FX)":5,"Mad Men (AMC)":6,"Justified (FX)":7,"Parks and Recreation (NBC)":8,"Scandal (ABC)":9,"Key and Peele (Comedy Central)":10}},"Mark Perigard":{"link":"http://bostonherald.com/entertainment/television/television_news/2013/12/lots_of_shows_worth_watching_in_2013","publication":"Boston Herald","list":{"American Horror Story (FX)":"_","Breaking Bad (AMC)":"_","Happy Endings (ABC)":"_","Homeland (Showtime)":"_","House of Cards (Netflix)":"_","It's Always Sunny in Philadelphia (FXX)":"_","Orphan Black (BBC America)":"_","Southland (TNT)":"_","Spartacus (Starz)":"_","The Walking Dead (AMC)":"_"}},"Lori Rackl":{"link":"http://voices.suntimes.com/arts-entertainment/the-daily-sizzle/lori-rackl-top-10-tv-shows-of-2013-both-old-and-new/","publication":"Chicago Sun-Times","list":{"Breaking Bad (AMC)":1,"Game of Thrones (HBO)":2,"Homeland (Showtime)":3,"American Horror Story (FX)":4,"The Americans (FX)":5,"Parks and Recreation (NBC)":6,"Mad Men (AMC)":7,"The Walking Dead (AMC)":8,"Scandal (ABC)":9,"Downton Abbey (PBS)":10}},"Mark Dawidziak":{"link":"http://www.cleveland.com/tv-blog/index.ssf/2013/12/justified_house_of_cards_masters_of_sex_lead_top_10_list_for_2013_tv_year_in_review.html","publication":"Cleveland Plain Dealer","list":{"Justified (FX)":1,"House of Cards (Netflix)":2,"Masters of Sex (Showtime)":3,"Breaking Bad (AMC)":4,"Ray Donovan (Showtime)":5,"The Blacklist (NBC)":6,"The Middle (ABC)":7,"Downton Abbey (PBS)":8,"Parenthood (NBC)":9,"The Walking Dead (AMC)":10}},"Complex":{"link":"http://www.complex.com/pop-culture/2013/12/best-tv-shows-2013/","list":{"Breaking Bad (AMC)":1,"Game of Thrones (HBO)":2,"American Horror Story (FX)":3,"Orange Is the New Black (Netflix)":4,"Boardwalk Empire (HBO)":5,"New Girl (Fox)":6,"Love and Hip-Hop: Atlanta (VH1)":7,"Veep (HBO)":8,"Eastbound & Down (HBO)":9,"Orphan Black (BBC America)":10}},"Chuck Barney":{"link":"http://www.mercurynews.com/entertainment/ci_24744717/best-2013-tv-top-10-shows-year","publication":"Contra Costa Times","list":{"Breaking Bad (AMC)":1,"Masters of Sex (Showtime)":2,"Game of Thrones (HBO)":3,"Orange Is the New Black (Netflix)":4,"The Good Wife (CBS)":5,"House of Cards (Netflix)":6,"Mad Men (AMC)":7,"The Americans (FX)":8,"Broadchurch (BBC America)":9,"The Returned (Sundance)":10}},"Kevin Fallon":{"link":"http://www.thedailybeast.com/articles/2013/12/13/the-best-tv-shows-of-2013-orange-is-the-new-black-breaking-bad-and-more.html","publication":"The Daily Beast","list":{"Orange Is the New Black (Netflix)":1,"Breaking Bad (AMC)":2,"Bob's Burgers (Fox)":3,"Veep (HBO)":4,"The Good Wife (CBS)":5,"Shameless (Showtime)":6,"Parks and Recreation (NBC)":7,"Scandal (ABC)":8,"American Horror Story (FX)":9,"The New Girl":10,"The Mindy Project":10}},"Jeff Jensen":{"publication":"Entertainment Weekly","list":{"American Horror Story (FX)":1,"Time of Death (Showtime)":2,"Orphan Black (BBC America)":3,"Parks and Recreation (NBC)":4,"Breaking Bad (AMC)":5,"Orange Is the New Black (Netflix)":6,"Mad Men (AMC)":7,"House of Cards (Netflix)":8,"The Fall (BBC2)":9,"Arrested Development (Netflix)":10}},"Melissa Maerz":{"publication":"Entertainment Weekly","list":{"Breaking Bad (AMC)":1,"Enlightened (HBO)":2,"Game of Thrones (HBO)":3,"Orange Is the New Black (Netflix)":4,"Please Like Me (Pivot)":5,"Mad Men (AMC)":6,"Top of the Lake (Sundance)":7,"The Good Wife (CBS)":8,"House of Cards (Netflix)":9,"The Returned (Sundance)":10}},"Inkoo Kang":{"link":"http://www.filmschoolrejects.com/features/best-tv-shows-of-2013.php","publication":"Film School Rejects","list":{"Breaking Bad (AMC)":1,"Orange Is the New Black (Netflix)":2,"Game of Thrones (HBO)":3,"Scandal (ABC)":4,"Enlightened (HBO)":5,"Masters of Sex (Showtime)":6,"Eastbound & Down (HBO)":7,"The Bridge (FX)":8,"Mad Men (AMC)":9,"Girls (HBO)":10}},"Dan Schoenbrun":{"link":"http://filmmakermagazine.com/82968-the-ten-best-tv-shows-of-2013/#.Ur4DpLQucwk","publication":"Filmmaker Magazine","list":{"Enlightened (HBO)":1,"The Eric Andre Show (Adult Swim)":2,"Breaking Bad (AMC)":3,"Hannibal (NBC)":4,"Rectify (Sundance)":5,"Mad Men (AMC)":6,"Adventure Time (Cartoon Network)":7,"Orange Is the New Black (Netflix)":8,"Game of Thrones (HBO)":9,"Eastbound & Down (HBO)":10}},"Andy Greenwald":{"link":"http://www.grantland.com/blog/hollywood-prospectus/post/_/id/95603/my-top-10-best-favorite-tv-shows-of-2013","publication":"Grantland","list":{"Top of the Lake (Sundance)":1,"The Americans (FX)":2,"Black Mirror (DirecTV)":3,"Breaking Bad (AMC)":4,"Orange Is the New Black (Netflix)":5,"Parks and Recreation (NBC)":6,"Masters of Sex (Showtime)":7,"Veep (HBO)":8,"Eastbound & Down (HBO)":9,"Girls (HBO)":10}},"Daniel Fienberg":{"link":"http://www.hitfix.com/the-fien-print/the-fien-prints-tv-top-10-for-2013-breaking-bad-sundances-big-year-and-more","publication":"HitFix","list":{"Breaking Bad (AMC)":1,"Orange Is the New Black (Netflix)":2,"Mad Men (AMC)":3,"Rectify (Sundance)":4,"The Returned (Sundance)":5,"Enlightened (HBO)":6,"Game of Thrones (HBO)":7,"Bob's Burgers (Fox)":8,"56 Up (PBS)":9,"Girls (HBO)":10}},"Alan Sepinwall":{"link":"http://www.hitfix.com/whats-alan-watching/tv-top-10-for-2013-breaking-bad-boardwalk-empire-more","publication":"HitFix","list":{"Breaking Bad (AMC)":1,"Orange Is the New Black (Netflix)":2,"Enlightened (HBO)":3,"Top of the Lake (Sundance)":4,"Masters of Sex (Showtime)":5,"Mad Men (AMC)":6,"Boardwalk Empire (HBO)":7,"Southland (TNT)":8,"Hannibal (NBC)":9,"The Good Wife (CBS)":10}},"Therese Odell":{"link":"http://www.chron.com/entertainment/tv/gallery/The-10-Best-Shows-of-2013-and-then-some-76436.php","publication":"Houston Chronicle","list":{"Breaking Bad (AMC)":1,"American Horror Story (FX)":2,"Game of Thrones (HBO)":3,"Mad Men (AMC)":4,"It's Always Sunny in Philadelphia (FXX)":5,"Arrested Development (Netflix)":6,"Hannibal (NBC)":7,"Orange Is the New Black (Netflix)":8,"Downton Abbey (PBS)":9,"The Blacklist (NBC)":10}},"Maureen Ryan":{"link":"http://www.huffingtonpost.com/maureen-ryan/best-tv-2013_b_4419561.html","publication":"Huffington Post","list":{"Borgen (various)":"_","Breaking Bad (AMC)":"_","Broadchurch (BBC America)":"_","Enlightened (HBO)":"_","Game of Thrones (HBO)":"_","Mad Men (AMC)":"_","Masters of Sex (Showtime)":"_","Orphan Black (BBC America)":"_","Orange Is the New Black (Netflix)":"_","Rectify (Sundance)":"_","The Returned (Sundance)":"_","Top of the Lake (Sundance)":"_"}},"":{"link":"http://www.ign.com/wikis/best-of-2013/Best_TV_Series","publication":"IGN","note":"all others unranked:","list":{"1. Breaking Bad (AMC)":1,"The Americans (FX)":"_","Arrow (CW)":"_","Game of Thrones (HBO)":"_","Hannibal (NBC)":"_","Masters of Sex (Showtime)":"_","Orange Is the New Black (Netflix)":"_","Orphan Black (BBC America)":"_","Parks and Recreation (NBC)":"_","Spartacus (Starz)":"_"}},"Alison Willmore":{"publication":"Indiewire","list":{"Breaking Bad (AMC)":1,"Orange Is the New Black (Netflix)":2,"Top of the Lake (Sundance)":3,"Enlightened (HBO)":4,"Scandal (ABC)":5,"Game of Thrones (HBO)":6,"The Americans (FX)":7,"Hannibal (NBC)":8,"Bob's Burgers (Fox)":9,"The Returned (Sundance)":10}},"Jeff Korbelik":{"link":"http://journalstar.com/entertainment/tv-radio/best-of-breaking-bad-netflix-top-tv-year/article_f1fa7e7a-499e-5762-adde-69c2827c295b.html","publication":"Lincoln Journal Star","list":{"Breaking Bad (AMC)":1,"Orphan Black (BBC America)":2,"House of Cards (Netflix)":3,"The Returned (Sundance)":4,"Orange Is the New Black (Netflix)":5,"The Fall (BBC2)":6,"The Walking Dead (AMC)":7,"Justified (FX)":8,"Mad Men (AMC)":9,"The Good Wife (CBS)":10}},"Robert Lloyd":{"link":"http://www.latimes.com/entertainment/tv/showtracker/la-et-st-robert-lloyd-best-tv-shows-2013-photos,0,1690981.photogallery","publication":"Los Angeles Times","list":{"The Returned (Sundance)":1,"Inside Amy Schumer (Comedy Central)":2,"Drunk History (Comedy Central)":3,"Top of the Lake (Sundance)":4,"Moone Boy (Hulu)":5,"Family Tree (HBO)":5,"MasterChef Junior (Fox)":6,"The Hollow Crown (PBS)":7,"Incredible Crew (Cartoon Network)":8,"Only the Young (PBS)":9,"Please Like Me (Pivot)":10,"The Fosters (ABC Family)":10}},"Mary McNamara":{"link":"http://www.latimes.com/entertainment/tv/showtracker/la-et-st-mary-mcnamara-best-tv-shows-2013-photos,0,6920016.photogallery","publication":"Los Angeles Times","list":{"Game of Thrones (HBO)":1,"Orange Is the New Black (Netflix)":2,"Breaking Bad (AMC)":3,"The Good Wife (CBS)":4,"Parks and Recreation (NBC)":5,"Rectify (Sundance)":6,"Enlightened (HBO)":7,"Borgen (various)":8,"Last Tango in Halifax (PBS)":9,"Homeland (Showtime)":10}},"Glenn Garvin":{"link":"http://www.miamiherald.com/static/media/projects/2013/year-in-review/","publication":"Miami Herald","list":{"Homeland (Showtime)":1,"The Americans (FX)":2,"Modern Family (ABC)":3,"The Big Bang Theory (CBS)":4,"Hostages (CBS)":5}},"Matt Zoller Seitz":{"link":"http://www.vulture.com/2013/12/matt-zoller-seitzs-10-best-tv-shows-of-2013.html","publication":"New York (Vulture)","list":{"Arrested Development (Netflix)":1,"Hannibal (NBC)":2,"Breaking Bad (AMC)":3,"Boardwalk Empire (HBO)":4,"Game of Thrones (HBO)":5,"Orange Is the New Black (Netflix)":6,"Girls (HBO)":7,"Justified (FX)":8,"Scandal (ABC)":9,"The Americans (FX)":10}},"David Hinckley":{"link":"http://www.nydailynews.com/entertainment/tv-movies/david-hinckley-best-television-2013-article-1.1550860","publication":"New York Daily News","list":{"Awkward (MTV)":"_","The Blacklist (NBC)":"_","Boardwalk Empire (HBO)":"_","Breaking Bad (AMC)":"_","Dancing on the Edge (Starz)":"_","Downton Abbey (PBS)":"_","Homeland (Showtime)":"_","Justified (FX)":"_","Mad Men (AMC)":"_","Sons of Anarchy (FX)":"_"}},"Mike Hale":{"link":"http://www.nytimes.com/2013/12/15/arts/television/mike-hales-top-12-television-shows-of-2013.html","publication":"The New York Times","list":{"The Good Wife (CBS)":1,"Prisoners of War (Hulu)":2,"Frontline (PBS)":3,"The Hollow Crown (PBS)":4,"The Newsroom (HBO)":5,"Grimm (NBC)":6,"Moone Boy (Hulu)":7,"The Americans (FX)":8,"Southland (TNT)":9,"The Walking Dead (AMC)":10}},"Verne Gay":{"link":"http://www.newsday.com/entertainment/tv/best-tv-shows-of-2013-1.6649121#1","publication":"Newsday","list":{"Breaking Bad (AMC)":1,"Game of Thrones (HBO)":2,"Mad Men (AMC)":3,"House of Cards (Netflix)":4,"Behind the Candelabra (HBO)":5,"The Americans (FX)":6,"Masters of Sex (Showtime)":7,"The African Americans: Many Rivers to Cross (PBS)":8,"The Returned (Sundance)":9,"Veep (HBO)":10,"Parks and Recreation (NBC)":10}},"Eric Deggans":{"link":"http://www.npr.org/blogs/monkeysee/2013/12/31/258413489/remote-control-it-was-hard-to-turn-off-the-tv-in-2013","publication":"NPR","list":{"Breaking Bad (AMC)":1,"Broadchurch (BBC America)":2,"House of Cards (Netflix)":3,"Game of Thrones (HBO)":4,"The Good Wife (CBS)":5,"The Walking Dead (AMC)":6,"John Oliver's guest hosting stint on The Daily Show":7,"Scandal (ABC)":8,"Orange Is the New Black (Netflix)":9,"The Bridge (FX)":10,"Doctor Who (BBC)":10,"The Returned (Sundance)":10}},"David Bianculli":{"link":"http://www.npr.org/2013/12/23/256615366/david-biancullis-top-10-shows-2013-was-a-good-year-for-tv","publication":"NPR (Fresh Air)","list":{"Breaking Bad (AMC)":1,"The Good Wife (CBS)":2,"Mad Men (AMC)":3,"Justified (FX)":4,"The Colbert Report (Comedy Central)":5,"The Walking Dead (AMC)":6,"House of Cards (Netflix)":7,"Masters of Sex (Showtime)":8,"Downton Abbey (PBS)":9,"Orange Is the New Black (Netflix)":10}},"Micah Mertes":{"link":"http://www.omaha.com/article/20131211/GO/131219830/1181#.UqpAprQUQXW","publication":"Omaha World-Herald","list":{"Breaking Bad (AMC)":1,"Justified (FX)":2,"The Good Wife (CBS)":3,"Arrow (CW)":4,"Orphan Black (BBC America)":5,"New Girl (Fox)":6,"Game of Thrones (HBO)":7,"The Americans (FX)":8,"Top of the Lake (Sundance)":9,"Person of Interest (CBS)":10}},"Kristi Turnquist":{"link":"http://www.oregonlive.com/movies/index.ssf/2013/12/top_10_tv_shows_of_2013_breaki.html","publication":"The Oregonian","list":{"Breaking Bad (AMC)":1,"Masters of Sex (Showtime)":2,"Broadchurch (BBC America)":3,"The Good Wife (CBS)":4,"Game of Thrones (HBO)":5,"House of Cards (Netflix)":6,"Mad Men (AMC)":7,"Orange Is the New Black (Netflix)":8,"The Americans (FX)":9,"Downton Abbey (PBS)":10}},"Hal Boedeker":{"link":"http://www.orlandosentinel.com/entertainment/blogs/tv-guy/os-2013-favorites-breaking-bad-good-wife-masters-of-sex-20131230,0,7407460.post","publication":"Orlando Sentinel","list":{"Breaking Bad (AMC)":1,"The Good Wife (CBS)":2,"Masters of Sex (Showtime)":3,"The Americans (FX)":4,"The Big Bang Theory (CBS)":5,"Broadchurch (BBC America)":6,"Justified (FX)":7,"Downton Abbey (PBS)":8,"The Walking Dead (AMC)":9,"Behind the Candelabra (HBO)":10}},"Josh Jackson":{"link":"http://www.pastemagazine.com/blogs/lists/2013/12/the-25-best-tv-shows-of-2013.html","publication":"Paste","list":{"Breaking Bad (AMC)":1,"Parks and Recreation (NBC)":2,"Mad Men (AMC)":3,"Orange Is the New Black (Netflix)":4,"Arrested Development (Netflix)":5,"Game of Thrones (HBO)":6,"House of Cards (Netflix)":7,"New Girl (Fox)":8,"Brooklyn Nine-Nine (Fox)":9,"Eastbound & Down (HBO)":10}},"Ellen Gray":{"link":"http://www.philly.com/philly/entertainment/20131231_TV_s_best_of_the_rest.html","publication":"Philadelphia Daily News","list":{"Breaking Bad (AMC)":1,"Game of Thrones (HBO)":2,"Top of the Lake (Sundance)":3,"The Good Wife (CBS)":4,"Masters of Sex (Showtime)":5,"Orange Is the New Black (Netflix)":6,"Rectify (Sundance)":7,"The Americans (FX)":8,"Treme (HBO)":9,"Shameless (Showtime)":10}},"Rob Owen":{"link":"http://www.post-gazette.com/ae/tv-radio/2013/12/19/BEST-TV-Southland/stories/201312190132","publication":"Pittsburgh Post-Gazette","list":{"Southland (TNT)":1,"Breaking Bad (AMC)":2,"The Americans (FX)":3,"Mad Men (AMC)":4,"The Good Wife (CBS)":5,"Orange Is the New Black (Netflix)":6,"Game of Thrones (HBO)":7,"Getting On (HBO)":8,"Downton Abbey (PBS)":9,"Bunheads (ABC Family)":10}},"-PopMatters":{"link":"http://www.popmatters.com/feature/177840-the-best-tv-shows-of-2013/P0","publication":"PopMatters","list":{"The Americans (FX)":1,"Breaking Bad (AMC)":2,"Orange Is the New Black (Netflix)":3,"The Bridge (FX)":4,"Justified (FX)":5,"The Killing (AMC)":6,"Mad Men (AMC)":7,"Brooklyn Nine-Nine (Fox)":8,"Treme (HBO)":9,"House of Cards (Netflix)":10}},"Curt Wagner":{"link":"http://articles.redeyechicago.com/2013-12-18/entertainment/45345349_1_broadchurch-thrones-fxx","publication":"RedEye Chicago","list":{"American Horror Story (FX)":"_","Arrested Development (Netflix)":"_","Breaking Bad (AMC)":"_","House of Cards (Netflix)":"_","Justified (FX)":"_","Orange Is the New Black (Netflix)":"_","Orphan Black (BBC America)":"_","Please Like Me (Pivot)":"_","Rectify (Sundance)":"_","The Returned (Sundance)":"_"}},"Jen Chaney":{"link":"http://www.salon.com/2013/12/30/blue_glow_awards_2013_salons_tv_critics_poll/","publication":"Salon","list":{"Enlightened (HBO)":1,"Breaking Bad (AMC)":2,"Top of the Lake (Sundance)":3,"Masters of Sex (Showtime)":4,"Orange Is the New Black (Netflix)":5,"Mad Men (AMC)":6,"Veep (HBO)":7,"Game of Thrones (HBO)":8,"Parenthood (NBC)":9,"The Bridge (FX)":10}},"Neil Drumming":{"link":"http://www.salon.com/2013/12/30/blue_glow_awards_2013_salons_tv_critics_poll/","publication":"Salon","list":{"Breaking Bad (AMC)":1,"Mad Men (AMC)":2,"Boardwalk Empire (HBO)":3,"The Good Wife (CBS)":4,"The Walking Dead (AMC)":5,"Parenthood (NBC)":6,"American Horror Story (FX)":7,"The Big Bang Theory (CBS)":8,"The Blacklist (NBC)":9,"Parks and Recreation (NBC)":10}},"Scott D. Pierce":{"link":"http://www.sltrib.com/sltrib/entertainment2/57282110-223/shows-series-wife-list.html.csp","publication":"The Salt Lake Tribune","list":{"The Good Wife (CBS)":1,"Game of Thrones (HBO)":2,"Breaking Bad (AMC)":3,"Broadchurch (BBC America)":4,"House of Cards (Netflix)":5,"Downton Abbey (PBS)":6,"The Big Bang Theory (CBS)":7,"Trophy Wife (ABC)":8,"Rectify (Sundance)":9,"Scandal (ABC)":10}},"David Wiegand":{"link":"http://www.sfgate.com/tv/article/Breaking-Bad-leads-top-10-TV-shows-of-2013-5094801.php","publication":"San Francisco Chronicle","list":{"Breaking Bad (AMC)":1,"Orange Is the New Black (Netflix)":2,"Broadchurch (BBC America)":3,"The Good Wife (CBS)":4,"Arrested Development (Netflix)":5,"Veep (HBO)":6,"Please Like Me (Pivot)":7,"The Returned (Sundance)":8,"Orphan Black (BBC America)":9,"Mob City (TNT)":10}},"-Slant":{"link":"http://www.slantmagazine.com/features/article/the-25-best-tv-shows-of-2013","publication":"Slant","list":{"Breaking Bad (AMC)":1,"Hannibal (NBC)":2,"Justified (FX)":3,"Game of Thrones (HBO)":4,"The Americans (FX)":5,"Girls (HBO)":6,"Archer (FX)":7,"Boardwalk Empire (HBO)":8,"Mad Men (AMC)":9,"House of Cards (Netflix)":10}},"Willa Paskin":{"link":"http://www.slate.com/articles/arts/television/2013/12/mad_men_borgen_breaking_bad_orange_is_the_new_black_willa_paskin_s_top_10.html","publication":"Slate","list":{"Borgen (various)":1,"Top of the Lake (Sundance)":2,"Orange Is the New Black (Netflix)":3,"Breaking Bad (AMC)":4,"The Good Wife (CBS)":5,"The Americans (FX)":6,"The Returned (Sundance)":7,"Bunheads (ABC Family)":8,"American Horror Story (FX)":9,"Mad Men (AMC)":10}},"Gail Pennington":{"link":"http://www.stltoday.com/gallery/entertainment/television/gail-pennington/top-tv-shows-of-breaking-bad-and-all-the-rest/collection_0f658635-8ac5-569b-9966-7d01ce1f6904.html#0","publication":"St. Louis Post-Dispatch","list":{"Breaking Bad (AMC)":1,"The Walking Dead (AMC)":2,"Game of Thrones (HBO)":3,"Mad Men (AMC)":4,"Broadchurch (BBC America)":5,"The Returned (Sundance)":6,"Downton Abbey (PBS)":7,"Orphan Black (BBC America)":8,"Parks and Recreation (NBC)":9,"Masters of Sex (Showtime)":10}},"James Poniewozik":{"link":"http://entertainment.time.com/2013/12/04/arts-and-entertainment/slide/top-10-tv-shows-2/","publication":"Time","list":{"Enlightened (HBO)":1,"Breaking Bad (AMC)":2,"Orange Is the New Black (Netflix)":3,"Game of Thrones (HBO)":4,"The Good Wife (CBS)":5,"Bob's Burgers (Fox)":6,"Rectify (Sundance)":7,"The Americans (FX)":8,"Mad Men (AMC)":9,"Orphan Black (BBC America)":10}},"Tim Surette":{"link":"http://www.tv.com/news/editors-picks-the-tvcom-staffs-top-10-shows-of-2013-138787314743/","publication":"TV.com","list":{"Breaking Bad (AMC)":1,"Enlightened (HBO)":2,"Justified (FX)":3,"Rectify (Sundance)":4,"The Americans (FX)":5,"Game of Thrones (HBO)":6,"Person of Interest (CBS)":7,"The Returned (Sundance)":8,"Comedy Bang! Bang! (IFC)":9,"Orange Is the New Black (Netflix)":10}},"Kaitlin Thomas":{"link":"http://www.tv.com/news/editors-picks-the-tvcom-staffs-top-10-shows-of-2013-138787314743/","publication":"TV.com","list":{"Breaking Bad (AMC)":1,"Justified (FX)":2,"Orphan Black (BBC America)":3,"Game of Thrones (HBO)":4,"The Americans (FX)":5,"Veep (HBO)":6,"Mad Men (AMC)":7,"Parks and Recreation (NBC)":8,"Teen Wolf (MTV)":9,"Arrow (CW)":10}},"Jen Trolio":{"link":"http://www.tv.com/news/editors-picks-the-tvcom-staffs-top-10-shows-of-2013-138787314743/","publication":"TV.com","list":{"The Americans (FX)":1,"Breaking Bad (AMC)":2,"Orange Is the New Black (Netflix)":3,"Game of Thrones (HBO)":4,"30 Rock (NBC)":5,"Parks and Recreation (NBC)":6,"Mad Men (AMC)":7,"Masters of Sex (Showtime)":8,"New Girl (Fox)":9,"American Horror Story (FX)":10}},"-TV Guide":{"link":"http://www.tvguide.com/PhotoGallery/Best-TV-Shows-2013-1074311","publication":"TV Guide","list":{"Breaking Bad (AMC)":1,"Orange Is the New Black (Netflix)":2,"The Good Wife (CBS)":3,"Game of Thrones (HBO)":4,"Mad Men (AMC)":5,"Veep (HBO)":6,"Masters of Sex (Showtime)":7,"The Americans (FX)":8,"Hannibal (NBC)":9,"House of Cards (Netflix)":10}},"Matt Roush":{"link":"http://www.tvguide.com/News/Matt-Roushs-10-1074816.aspx","publication":"TV Guide","list":{"Breaking Bad (AMC)":1,"The Good Wife (CBS)":2,"Broadchurch (BBC America)":3,"Masters of Sex (Showtime)":4,"Orange Is the New Black (Netflix)":5,"various Sundance Channel shows":6,"The Americans (FX)":7,"Game of Thrones (HBO)":8,"sitcom oldies and goodies":9,"Ray Donovan (Showtime)":10}},"Ed Bark":{"link":"http://unclebarky.com/list_files/875ada48dfdbabe7592f9a488bc4744a-48.html","publication":"Uncle Barky","list":{"Breaking Bad (AMC)":1,"Game of Thrones (HBO)":2,"Masters of Sex (Showtime)":3,"Mad Men (AMC)":4,"Justified (FX)":5,"The Americans (FX)":6,"Orange Is the New Black (Netflix)":7,"House of Cards (Netflix)":8,"The Middle (ABC)":9,"Homeland (Showtime)":10}},"John Griffiths":{"link":"http://www.usmagazine.com/entertainment/news/top-10-tv-shows-of-2013-30-rock-scandal-breaking-bad-20131812","publication":"Us Weekly","list":{"Mad Men (AMC)":1,"Breaking Bad (AMC)":2,"Orphan Black (BBC America)":3,"The Good Wife (CBS)":4,"Scandal (ABC)":5,"30 Rock (NBC)":6,"House of Cards (Netflix)":7,"The Walking Dead (AMC)":8,"Behind the Candelabra (HBO)":9,"Bates Motel (A&E)":10}},"Robert Bianco":{"link":"http://www.usatoday.com/story/life/tv/2013/12/29/tv-best-of-2013/3957727/","publication":"USA Today","list":{"Breaking Bad (AMC)":1,"The Big Bang Theory (CBS)":2,"The Good Wife (CBS)":2,"Modern Family (ABC)":4,"Justified (FX)":5,"The Americans (FX)":6,"Masters of Sex (Showtime)":7,"Broadchurch (BBC America)":8,"The Middle (ABC)":9,"Downton Abbey (PBS)":10}},"Brian Lowery":{"link":"http://variety.com/gallery/best-tv-shows-of-2013/#!1/introduction-top-12-shows-of-the-year/","publication":"Variety","list":{"Breaking Bad (AMC)":1,"Game of Thrones (HBO)":2,"Boardwalk Empire (HBO)":3,"Downton Abbey (PBS)":4,"Southland (TNT)":5,"The Big Bang Theory (CBS)":6,"The Walking Dead (AMC)":7,"Modern Family (ABC)":8,"The Good Wife (CBS)":9,"Masters of Sex (Showtime)":10}},"Dorothy Rabinowitz":{"link":"http://online.wsj.com/news/articles/SB10001424052702303290904579276500260994522","publication":"Wall Street Journal","list":{"The Americans (FX)":"_","Behind the Candelabra (HBO)":"_","The Blacklist (NBC)":"_","The Crash Reel (HBO)":"_","Hostages (CBS)":"_","Lilyhammer (Netflix)":"_","Our Nixon (CNN)":"_","The Paradise (PBS)":"_","Ray Donovan (Showtime)":"_"}},"Hank Stuever":{"link":"http://www.washingtonpost.com/sf/style/2013/12/06/best-tv-shows-of-2013/","publication":"Washington Post","list":{"Breaking Bad (specifically, Walter White's exit strategy)":1,"Orange Is the New Black (Netflix)":2,"Masters of Sex (Showtime)":3,"\"Red Wedding\" episode of Game of Thrones (HBO)":4,"Time of Death (Showtime)":5,"Broadchurch (BBC America)":6,"The Americans (FX)":7,"Vikings (History)":8,"The Returned (Sundance)":9,"Veep (HBO)":10}},"-Yahoo! TV":{"link":"http://tv.yahoo.com/photos/best-shows-of-2013-slideshow/#mm","publication":"Yahoo! TV","list":{"Breaking Bad (AMC)":1,"Game of Thrones (HBO)":2,"Mad Men (AMC)":3,"Orange Is the New Black (Netflix)":4,"Parks and Recreation (NBC)":5,"Scandal (ABC)":6,"Hello Ladies (HBO)":7,"Veep (HBO)":8,"The Walking Dead (AMC)":9,"Orphan Black (BBC America)":10}}}