{"Ida":{"year":"2014","notSameYear":"2013"},"The Immigrant":{"year":"2014","notSameYear":"2013"},"Under the Skin":{"year":"2014","notSameYear":"2013"},"Stranger by the Lake":{"year":"2014","notSameYear":"2013"},"Nymphomaniac":{"year":"2014","notSameYear":"2010"},"Norte, The End of History":{"year":"2014","notSameYear":"2013"},"Starred Up":{"year":"2014","notSameYear":"2013"},"Her":{"year":"2014","notSameYear":"2013"},"The Americans [TV series]":{"year":"2014"},"The Marx Brothers TV Collection [DVD box set]":{"year":"2014"},"The Congress":{"year":"2014","notSameYear":"2013"},"A Summer's Tale":{"year":"2014","notSameYear":"1996"},"Story of My Death":{"year":"2014","notSameYear":"2013"},"Final Cut: Ladies and Gentlemen":{"year":"2014","notSameYear":"2012"},"It Felt Like Love":{"year":"2014","notSameYear":"2013"},"Level Five":{"year":"2014","notSameYear":"1997"},"Big Men":{"year":"2014","notSameYear":"2013"},"The Knick [TV series]":{"year":"2014"},"Jodorowsky's Dune":{"year":"2014","notSameYear":"2013"},"Locke":{"year":"2014","notSameYear":"2013"},"Proxy":{"year":"2014","notSameYear":"2013"},"The Missing Picture":{"year":"2014","notSameYear":"2013"},"Only Lovers Left Alive":{"year":"2014","notSameYear":"2013"},"Stray Dogs":{"year":"2014","notSameYear":"2013"},"The Strange Little Cat":{"year":"2014","notSameYear":"2013"},"Butter on the Latch":{"year":"2014","notSameYear":"2013"},"Lesson of the Evil":{"year":"2014","notSameYear":"2012"},"The Last of the Unjust":{"year":"2014","notSameYear":"2013"},"Nothing Bad Can Happen":{"year":"2014","notSameYear":"2013"},"Manuscripts Don't Burn":{"year":"2014","notSameYear":"2013"},"The Dance of Reality":{"year":"2014","notSameYear":"2013"},"Cheap Thrills":{"year":"2014","notSameYear":"2013"},"Belle":{"year":"2014","notSameYear":"2013"},"The Unknown Known":{"year":"2014","notSameYear":"2013"},"Child's Pose":{"year":"2014","notSameYear":"2013"},"Inside Llewyn Davis":{"year":"2014","notSameYear":"2013"},"Rambleras":{"year":"2014","notSameYear":"2013"},"Vic + Flo Saw a Bear":{"year":"2014","notSameYear":"2013"},"The Wolf of Wall Street":{"year":"2014","notSameYear":"2013"},"Thy Womb":{"year":"2014","notSameYear":"2012"},"What Now? Remind Me":{"year":"2014","notSameYear":"2013"},"Farbe":{"year":"2014","notSameYear":"2003"},"A Spell to Ward Off the Darkness":{"year":"2014","notSameYear":"2013"},"The Kindergarten Teacher":{"year":"2014","notSameYear":"2018"},"Last of the Unjust":{"year":"2014","notSameYear":"2013"},"12 Years a Slave":{"year":"2014","notSameYear":"2013"},"Particle Fever":{"year":"2014","notSameYear":"2013"},"Northern Light":{"year":"2014","notSameYear":"2006"},"Class Enemy":{"year":"2014","notSameYear":"2013"},"Alan Partridge: Alpha Papa":{"year":"2014"},"Le Week-end":{"year":"2014","notSameYear":"2013"},"Begin Again":{"year":"2014","notSameYear":"2013"},"Patema Inverted":{"year":"2014","notSameYear":"2013"},"Ilo Ilo":{"year":"2014","notSameYear":"2013"},"P'tit Quinquin":{"year":"2014"},"Snowpiercer":{"year":"2014","notSameYear":"2013"},"Mistaken for Strangers":{"year":"2014","notSameYear":"2013"},"Joe":{"year":"2014","notSameYear":"2013"},"Coherence":{"year":"2014","notSameYear":"2013"},"Blue Ruin":{"year":"2014","notSameYear":"2013"},"Borgman":{"year":"2014","notSameYear":"2013"},"Memphis":{"year":"2014","notSameYear":"2013"},"See You Next Tuesday":{"year":"2014","notSameYear":"2013"},"Antarctica":{"year":"2014","notSameYear":"1983"},"Das Spektrum Europas":{"year":"2014"},"Policeman":{"year":"2014","notSameYear":"2011"},"Heli":{"year":"2014","notSameYear":"2013"},"The Retrieval":{"year":"2014","notSameYear":"2013"},"Hateship Loveship":{"year":"2014","notSameYear":"2013"},"Enemy":{"year":"2014","notSameYear":"2013"},"Why Don't You Play in Hell?":{"year":"2014","notSameYear":"2013"},"Revenge of the Mekons":{"year":"2014","notSameYear":"2013"},"The Lunchbox":{"year":"2014","notSameYear":"2013"},"Stand Clear of the Closing Doors":{"year":"2014","notSameYear":"2013"},"We Are the Best!":{"year":"2014","notSameYear":"2013"},"Manakamana":{"year":"2014","notSameYear":"2013"},"A Field in England":{"year":"2014","notSameYear":"2013"},"The Tale of the Princess Kaguya":{"year":"2014","notSameYear":"2013"},"The Wind Rises":{"year":"2014","notSameYear":"2013"},"Le Paradis":{"year":"2014","notSameYear":"1914"},"Our Sunhi":{"year":"2014","notSameYear":"2013"},"Jealousy":{"year":"2014","notSameYear":"2013"},"Everyday":{"year":"2014","notSameYear":"2012"},"The Kill Team":{"year":"2014","notSameYear":"2019"},"Breakfast With Curtis":{"year":"2014","notSameYear":"2012"},"Jimmy P.":{"year":"2014","notSameYear":"2013"},"Mood Indigo":{"year":"2014","notSameYear":"2013"},"Flamenco Flamenco":{"year":"2014","notSameYear":"2010"},"Journey to the West":{"year":"2014","notSameYear":"2013"},"Abuse of Weakness":{"year":"2014","notSameYear":"2013"},"Night Moves":{"year":"2014","notSameYear":"2013"},"Witching and Bitching":{"year":"2014","notSameYear":"2013"},"Third Person":{"year":"2014","notSameYear":"2013"},"Kids for Cash":{"year":"2014","notSameYear":"2013"},"Salt of the Earth":{"year":"2014","notSameYear":"1954"},"The Amazing Catfish":{"year":"2014","notSameYear":"2013"},"Thursday Till Sunday":{"year":"2014","notSameYear":"2012"},"nherent Vice":{"year":"2014"},"The Double":{"year":"2014","notSameYear":"2013"},"Tracks":{"year":"2014","notSameYear":"2013"},"Exhibition":{"year":"2014","notSameYear":"2013"},"Ernest & Celestine":{"year":"2014","notSameYear":"2002"},"Bad Hair":{"year":"2014","notSameYear":"2013"},"The Selfish Giant":{"year":"2014","notSameYear":"2013"},"Violette":{"year":"2014","notSameYear":"1978"},"Like Father, Like Son":{"year":"2014","notSameYear":"2011"},"The Galapagos Affair":{"year":"2014","notSameYear":"2016"},"Tip Top":{"year":"2014","notSameYear":"2013"},"Venus in Fur":{"year":"2014","notSameYear":"2013"}}